{
  "updatedAt": "2026-07-01T02:34:26+00:00",
  "source": "the-odds-api",
  "currentRound": "R32",
  "players": [
    {
      "id": "paul",
      "name": "Paul",
      "color": "#e6394a",
      "teams": [
        "Spain",
        "Ecuador",
        "Algeria",
        "Scotland",
        "Panama"
      ],
      "prevRank": 6
    },
    {
      "id": "caoimh",
      "name": "Caoimh",
      "color": "#f76707",
      "teams": [
        "France",
        "Mexico",
        "Uruguay",
        "Paraguay",
        "Iran",
        "Uzbekistan"
      ],
      "prevRank": 1
    },
    {
      "id": "fran",
      "name": "Fran",
      "color": "#2f9e44",
      "teams": [
        "England",
        "Norway",
        "Japan",
        "Türkiye",
        "Canada",
        "Egypt",
        "DR Congo",
        "Jordan",
        "Saudi Arabia",
        "Haiti"
      ],
      "prevRank": 3
    },
    {
      "id": "kev",
      "name": "Kev",
      "color": "#1c7ed6",
      "teams": [
        "Portugal",
        "Belgium",
        "Morocco",
        "USA",
        "Sweden",
        "Czechia",
        "Ghana",
        "Cape Verde",
        "Qatar",
        "Curaçao"
      ],
      "prevRank": 4
    },
    {
      "id": "dave",
      "name": "Dave",
      "color": "#7048e8",
      "teams": [
        "Argentina",
        "Germany",
        "Senegal",
        "Croatia",
        "Bosnia",
        "Korea Republic",
        "Tunisia"
      ],
      "prevRank": 2
    },
    {
      "id": "dec",
      "name": "Dec",
      "color": "#ffd43b",
      "teams": [
        "Brazil",
        "Netherlands",
        "Colombia",
        "Switzerland",
        "Austria",
        "Ivory Coast",
        "Australia",
        "Iraq",
        "New Zealand",
        "South Africa"
      ],
      "prevRank": 5
    }
  ],
  "teams": {
    "Spain": {
      "owner": "paul",
      "winProb": 0.10483,
      "alive": true,
      "reach": {
        "R32": 1.0,
        "R16": 0.884,
        "QF": 0.51509,
        "SF": 0.35409,
        "F": 0.18136,
        "W": 0.10482
      }
    },
    "Ecuador": {
      "owner": "paul",
      "winProb": 0.00634,
      "alive": true,
      "reach": {
        "R32": 1.0,
        "R16": 0.029,
        "QF": 0.01909,
        "SF": 0.01381,
        "F": 0.00991,
        "W": 0.00634
      }
    },
    "Algeria": {
      "owner": "paul",
      "winProb": 0.00179,
      "alive": true,
      "reach": {
        "R32": 1.0,
        "R16": 0.339,
        "QF": 0.12095,
        "SF": 0.03233,
        "F": 0.00827,
        "W": 0.00179
      }
    },
    "Scotland": {
      "owner": "paul",
      "winProb": 0.0,
      "alive": false,
      "reach": {}
    },
    "Panama": {
      "owner": "paul",
      "winProb": 0.0,
      "alive": false,
      "reach": {}
    },
    "France": {
      "owner": "caoimh",
      "winProb": 0.29295,
      "alive": true,
      "reach": {
        "R32": 1.0,
        "R16": 1.0,
        "QF": 0.928,
        "SF": 0.70344,
        "F": 0.4567,
        "W": 0.29291
      }
    },
    "Mexico": {
      "owner": "caoimh",
      "winProb": 0.02172,
      "alive": true,
      "reach": {
        "R32": 1.0,
        "R16": 0.971,
        "QF": 0.34429,
        "SF": 0.14545,
        "F": 0.06314,
        "W": 0.02172
      }
    },
    "Uruguay": {
      "owner": "caoimh",
      "winProb": 0.0,
      "alive": false,
      "reach": {}
    },
    "Paraguay": {
      "owner": "caoimh",
      "winProb": 0.0032,
      "alive": true,
      "reach": {
        "R32": 1.0,
        "R16": 1.0,
        "QF": 0.072,
        "SF": 0.03157,
        "F": 0.01016,
        "W": 0.0032
      }
    },
    "Iran": {
      "owner": "caoimh",
      "winProb": 0.0,
      "alive": false,
      "reach": {}
    },
    "Uzbekistan": {
      "owner": "caoimh",
      "winProb": 0.0,
      "alive": false,
      "reach": {}
    },
    "England": {
      "owner": "fran",
      "winProb": 0.10718,
      "alive": true,
      "reach": {
        "R32": 1.0,
        "R16": 0.909,
        "QF": 0.59901,
        "SF": 0.35637,
        "F": 0.21227,
        "W": 0.10718
      }
    },
    "Norway": {
      "owner": "fran",
      "winProb": 0.02448,
      "alive": true,
      "reach": {
        "R32": 1.0,
        "R16": 1.0,
        "QF": 0.313,
        "SF": 0.13637,
        "F": 0.06439,
        "W": 0.02448
      }
    },
    "Japan": {
      "owner": "fran",
      "winProb": 0.0,
      "alive": false,
      "reach": {
        "R32": 1.0
      }
    },
    "Türkiye": {
      "owner": "fran",
      "winProb": 0.0,
      "alive": false,
      "reach": {}
    },
    "Canada": {
      "owner": "fran",
      "winProb": 0.00446,
      "alive": true,
      "reach": {
        "R32": 1.0,
        "R16": 1.0,
        "QF": 0.273,
        "SF": 0.05344,
        "F": 0.01561,
        "W": 0.00446
      }
    },
    "Egypt": {
      "owner": "fran",
      "winProb": 0.00254,
      "alive": true,
      "reach": {
        "R32": 1.0,
        "R16": 0.574,
        "QF": 0.11982,
        "SF": 0.0463,
        "F": 0.0118,
        "W": 0.00254
      }
    },
    "DR Congo": {
      "owner": "fran",
      "winProb": 0.00132,
      "alive": true,
      "reach": {
        "R32": 1.0,
        "R16": 0.091,
        "QF": 0.03762,
        "SF": 0.01306,
        "F": 0.00474,
        "W": 0.00132
      }
    },
    "Jordan": {
      "owner": "fran",
      "winProb": 0.0,
      "alive": false,
      "reach": {}
    },
    "Saudi Arabia": {
      "owner": "fran",
      "winProb": 0.0,
      "alive": false,
      "reach": {}
    },
    "Haiti": {
      "owner": "fran",
      "winProb": 0.0,
      "alive": false,
      "reach": {}
    },
    "Portugal": {
      "owner": "kev",
      "winProb": 0.0606,
      "alive": true,
      "reach": {
        "R32": 1.0,
        "R16": 0.736,
        "QF": 0.35795,
        "SF": 0.23425,
        "F": 0.11176,
        "W": 0.06059
      }
    },
    "Belgium": {
      "owner": "kev",
      "winProb": 0.01464,
      "alive": true,
      "reach": {
        "R32": 1.0,
        "R16": 0.626,
        "QF": 0.31072,
        "SF": 0.11005,
        "F": 0.03719,
        "W": 0.01464
      }
    },
    "Morocco": {
      "owner": "kev",
      "winProb": 0.03501,
      "alive": true,
      "reach": {
        "R32": 1.0,
        "R16": 1.0,
        "QF": 0.727,
        "SF": 0.21154,
        "F": 0.08691,
        "W": 0.03501
      }
    },
    "USA": {
      "owner": "kev",
      "winProb": 0.02503,
      "alive": true,
      "reach": {
        "R32": 1.0,
        "R16": 0.861,
        "QF": 0.46187,
        "SF": 0.1717,
        "F": 0.06083,
        "W": 0.02503
      }
    },
    "Sweden": {
      "owner": "kev",
      "winProb": 0.0,
      "alive": false,
      "reach": {
        "R32": 1.0
      }
    },
    "Czechia": {
      "owner": "kev",
      "winProb": 0.0,
      "alive": false,
      "reach": {}
    },
    "Ghana": {
      "owner": "kev",
      "winProb": 0.00186,
      "alive": true,
      "reach": {
        "R32": 1.0,
        "R16": 0.169,
        "QF": 0.08276,
        "SF": 0.02522,
        "F": 0.00745,
        "W": 0.00186
      }
    },
    "Cape Verde": {
      "owner": "kev",
      "winProb": 0.00132,
      "alive": true,
      "reach": {
        "R32": 1.0,
        "R16": 0.062,
        "QF": 0.03525,
        "SF": 0.01603,
        "F": 0.005,
        "W": 0.00132
      }
    },
    "Qatar": {
      "owner": "kev",
      "winProb": 0.0,
      "alive": false,
      "reach": {}
    },
    "Curaçao": {
      "owner": "kev",
      "winProb": 0.0,
      "alive": false,
      "reach": {}
    },
    "Argentina": {
      "owner": "dave",
      "winProb": 0.16242,
      "alive": true,
      "reach": {
        "R32": 1.0,
        "R16": 0.938,
        "QF": 0.75456,
        "SF": 0.54298,
        "F": 0.31513,
        "W": 0.16247
      }
    },
    "Germany": {
      "owner": "dave",
      "winProb": 0.0,
      "alive": false,
      "reach": {
        "R32": 1.0
      }
    },
    "Senegal": {
      "owner": "dave",
      "winProb": 0.00561,
      "alive": true,
      "reach": {
        "R32": 1.0,
        "R16": 0.374,
        "QF": 0.16861,
        "SF": 0.05296,
        "F": 0.01593,
        "W": 0.00561
      }
    },
    "Croatia": {
      "owner": "dave",
      "winProb": 0.00456,
      "alive": true,
      "reach": {
        "R32": 1.0,
        "R16": 0.264,
        "QF": 0.08299,
        "SF": 0.03947,
        "F": 0.01241,
        "W": 0.00456
      }
    },
    "Bosnia": {
      "owner": "dave",
      "winProb": 0.00132,
      "alive": true,
      "reach": {
        "R32": 1.0,
        "R16": 0.139,
        "QF": 0.0588,
        "SF": 0.01613,
        "F": 0.00426,
        "W": 0.00132
      }
    },
    "Korea Republic": {
      "owner": "dave",
      "winProb": 0.0,
      "alive": false,
      "reach": {}
    },
    "Tunisia": {
      "owner": "dave",
      "winProb": 0.0,
      "alive": false,
      "reach": {}
    },
    "Brazil": {
      "owner": "dec",
      "winProb": 0.07521,
      "alive": true,
      "reach": {
        "R32": 1.0,
        "R16": 1.0,
        "QF": 0.687,
        "SF": 0.33495,
        "F": 0.17501,
        "W": 0.07521
      }
    },
    "Netherlands": {
      "owner": "dec",
      "winProb": 0.0,
      "alive": false,
      "reach": {
        "R32": 1.0
      }
    },
    "Colombia": {
      "owner": "dec",
      "winProb": 0.02785,
      "alive": true,
      "reach": {
        "R32": 1.0,
        "R16": 0.831,
        "QF": 0.50305,
        "SF": 0.20276,
        "F": 0.08108,
        "W": 0.02787
      }
    },
    "Switzerland": {
      "owner": "dec",
      "winProb": 0.00919,
      "alive": true,
      "reach": {
        "R32": 1.0,
        "R16": 0.661,
        "QF": 0.29323,
        "SF": 0.09901,
        "F": 0.03268,
        "W": 0.00918
      }
    },
    "Austria": {
      "owner": "dec",
      "winProb": 0.00259,
      "alive": true,
      "reach": {
        "R32": 1.0,
        "R16": 0.116,
        "QF": 0.04396,
        "SF": 0.02134,
        "F": 0.00688,
        "W": 0.00259
      }
    },
    "Ivory Coast": {
      "owner": "dec",
      "winProb": 0.0,
      "alive": false,
      "reach": {
        "R32": 1.0
      }
    },
    "Australia": {
      "owner": "dec",
      "winProb": 0.002,
      "alive": true,
      "reach": {
        "R32": 1.0,
        "R16": 0.426,
        "QF": 0.09036,
        "SF": 0.03536,
        "F": 0.00915,
        "W": 0.002
      }
    },
    "Iraq": {
      "owner": "dec",
      "winProb": 0.0,
      "alive": false,
      "reach": {}
    },
    "New Zealand": {
      "owner": "dec",
      "winProb": 0.0,
      "alive": false,
      "reach": {}
    },
    "South Africa": {
      "owner": "dec",
      "winProb": 0.0,
      "alive": false,
      "reach": {
        "R32": 1.0
      }
    }
  },
  "bracket": {
    "R32": [
      {
        "id": "r32-1",
        "teamA": "Germany",
        "teamB": "Paraguay",
        "probA": 0.879,
        "probB": 0.121,
        "winner": "B",
        "kickoff": "2026-06-29T20:30:00Z",
        "score": "1–1 p"
      },
      {
        "id": "r32-2",
        "teamA": "France",
        "teamB": "Sweden",
        "probA": 0.995,
        "probB": 0.005,
        "winner": "A",
        "kickoff": "2026-06-30T21:00:00Z",
        "score": "3–0"
      },
      {
        "id": "r32-3",
        "teamA": "Canada",
        "teamB": "South Africa",
        "probA": 0.726,
        "probB": 0.274,
        "winner": "A",
        "kickoff": "2026-06-28T19:00:00Z",
        "score": "1–0"
      },
      {
        "id": "r32-4",
        "teamA": "Netherlands",
        "teamB": "Morocco",
        "probA": 0.597,
        "probB": 0.403,
        "winner": "B",
        "kickoff": "2026-06-30T01:00:00Z",
        "score": "1–1 p"
      },
      {
        "id": "r32-5",
        "teamA": "Portugal",
        "teamB": "Croatia",
        "probA": 0.736,
        "probB": 0.264,
        "winner": null,
        "kickoff": "2026-07-02T23:00:00Z"
      },
      {
        "id": "r32-6",
        "teamA": "Spain",
        "teamB": "Austria",
        "probA": 0.884,
        "probB": 0.116,
        "winner": null,
        "kickoff": "2026-07-02T19:00:00Z"
      },
      {
        "id": "r32-7",
        "teamA": "USA",
        "teamB": "Bosnia",
        "probA": 0.861,
        "probB": 0.139,
        "winner": null,
        "kickoff": "2026-07-02T00:00:00Z"
      },
      {
        "id": "r32-8",
        "teamA": "Belgium",
        "teamB": "Senegal",
        "probA": 0.626,
        "probB": 0.374,
        "winner": null,
        "kickoff": "2026-07-01T20:00:00Z"
      },
      {
        "id": "r32-9",
        "teamA": "Brazil",
        "teamB": "Japan",
        "probA": 0.751,
        "probB": 0.249,
        "winner": "A",
        "kickoff": "2026-06-29T17:00:00Z",
        "score": "2–1"
      },
      {
        "id": "r32-10",
        "teamA": "Norway",
        "teamB": "Ivory Coast",
        "probA": 0.869,
        "probB": 0.131,
        "winner": "A",
        "kickoff": "2026-06-30T17:00:00Z",
        "score": "2–1"
      },
      {
        "id": "r32-11",
        "teamA": "Mexico",
        "teamB": "Ecuador",
        "probA": 0.971,
        "probB": 0.029,
        "winner": null,
        "kickoff": "2026-07-01T02:00:00Z"
      },
      {
        "id": "r32-12",
        "teamA": "England",
        "teamB": "DR Congo",
        "probA": 0.909,
        "probB": 0.091,
        "winner": null,
        "kickoff": "2026-07-01T16:00:00Z"
      },
      {
        "id": "r32-13",
        "teamA": "Argentina",
        "teamB": "Cape Verde",
        "probA": 0.938,
        "probB": 0.062,
        "winner": null,
        "kickoff": "2026-07-03T22:00:00Z"
      },
      {
        "id": "r32-14",
        "teamA": "Egypt",
        "teamB": "Australia",
        "probA": 0.574,
        "probB": 0.426,
        "winner": null,
        "kickoff": "2026-07-03T18:00:00Z"
      },
      {
        "id": "r32-15",
        "teamA": "Switzerland",
        "teamB": "Algeria",
        "probA": 0.661,
        "probB": 0.339,
        "winner": null,
        "kickoff": "2026-07-03T03:00:00Z"
      },
      {
        "id": "r32-16",
        "teamA": "Colombia",
        "teamB": "Ghana",
        "probA": 0.831,
        "probB": 0.169,
        "winner": null,
        "kickoff": "2026-07-04T01:30:00Z"
      }
    ],
    "R16": [
      {
        "id": "r16-1",
        "teamA": "Paraguay",
        "teamB": "France",
        "probA": 0.072,
        "probB": 0.928,
        "winner": null,
        "kickoff": "2026-07-04T21:00:00Z"
      },
      {
        "id": "r16-2",
        "teamA": "Canada",
        "teamB": "Morocco",
        "probA": 0.273,
        "probB": 0.727,
        "winner": null,
        "kickoff": "2026-07-04T17:00:00Z"
      },
      {
        "id": "r16-3",
        "teamA": null,
        "teamB": null,
        "probA": null,
        "probB": null,
        "winner": null,
        "kickoff": null
      },
      {
        "id": "r16-4",
        "teamA": null,
        "teamB": null,
        "probA": null,
        "probB": null,
        "winner": null,
        "kickoff": null
      },
      {
        "id": "r16-5",
        "teamA": "Brazil",
        "teamB": "Norway",
        "probA": 0.687,
        "probB": 0.313,
        "winner": null,
        "kickoff": "2026-07-05T20:00:00Z"
      },
      {
        "id": "r16-6",
        "teamA": null,
        "teamB": null,
        "probA": null,
        "probB": null,
        "winner": null,
        "kickoff": null
      },
      {
        "id": "r16-7",
        "teamA": null,
        "teamB": null,
        "probA": null,
        "probB": null,
        "winner": null,
        "kickoff": null
      },
      {
        "id": "r16-8",
        "teamA": null,
        "teamB": null,
        "probA": null,
        "probB": null,
        "winner": null,
        "kickoff": null
      }
    ],
    "QF": [
      {
        "id": "qf-1",
        "teamA": null,
        "teamB": null,
        "probA": null,
        "probB": null,
        "winner": null,
        "kickoff": null
      },
      {
        "id": "qf-2",
        "teamA": null,
        "teamB": null,
        "probA": null,
        "probB": null,
        "winner": null,
        "kickoff": null
      },
      {
        "id": "qf-3",
        "teamA": null,
        "teamB": null,
        "probA": null,
        "probB": null,
        "winner": null,
        "kickoff": null
      },
      {
        "id": "qf-4",
        "teamA": null,
        "teamB": null,
        "probA": null,
        "probB": null,
        "winner": null,
        "kickoff": null
      }
    ],
    "SF": [
      {
        "id": "sf-1",
        "teamA": null,
        "teamB": null,
        "probA": null,
        "probB": null,
        "winner": null,
        "kickoff": null
      },
      {
        "id": "sf-2",
        "teamA": null,
        "teamB": null,
        "probA": null,
        "probB": null,
        "winner": null,
        "kickoff": null
      }
    ],
    "F": [
      {
        "id": "f-1",
        "teamA": null,
        "teamB": null,
        "probA": null,
        "probB": null,
        "winner": null,
        "kickoff": null
      }
    ]
  },
  "postFetched": [
    "r32-3"
  ],
  "oddsCheckedAt": "2026-07-01T02:34:26+00:00"
}